mattrousseau_de_toolkit/__init__.py
mattrousseau_de_toolkit/main.py
mattrousseau_de_toolkit/vm.py
mattrousseau_de_toolkit-0.4.0.dist-info/METADATA
mattrousseau_de_toolkit-0.4.0.dist-info/WHEEL
mattrousseau_de_toolkit-0.4.0.dist-info/entry_points.txt
mattrousseau_de_toolkit-0.4.0.dist-info/RECORD
